masonite_fixtures/__init__.py
masonite_fixtures/masonite_fixtures.py
masonite_fixtures-0.0.5.dist-info/METADATA
masonite_fixtures-0.0.5.dist-info/WHEEL
masonite_fixtures-0.0.5.dist-info/top_level.txt
masonite_fixtures-0.0.5.dist-info/RECORD
