Metadata-Version: 2.1
Name: masonite-fixtures
Version: 0.0.5
Summary: Package provides utilities for managing fixture data python applications. It offers a convenient way to populate database tables with predefined data.
Home-page: https://github.com/JarriqTheTechie/masonite-fixtures
Author: Jarriq Rolle
Author-email: jrolle@bnbbahamas.com
Classifier: Programming Language :: Python :: 3
Classifier: License :: OSI Approved :: MIT License
Classifier: Operating System :: OS Independent
Requires-Python: >=3.9
Requires-Dist: masonite-orm
